huichao_poetry_demo/__init__.py
huichao_poetry_demo/main.py
huichao_poetry_demo-0.1.2.dist-info/WHEEL
huichao_poetry_demo-0.1.2.dist-info/METADATA
huichao_poetry_demo-0.1.2.dist-info/RECORD
